process_gpt_mcp/__init__.py
process_gpt_mcp/mcp_debug.log
process_gpt_mcp/server.py
process_gpt_mcp-0.1.6.dist-info/METADATA
process_gpt_mcp-0.1.6.dist-info/WHEEL
process_gpt_mcp-0.1.6.dist-info/entry_points.txt
process_gpt_mcp-0.1.6.dist-info/RECORD
